RLInventoryOpt/__init__.py
RLInventoryOpt/qlearning.py
RLInventoryOpt/utils/__init__.py
RLInventoryOpt/utils/inference.py
RLInventoryOpt/utils/plotting.py
rlinventoryopt-0.1.6.dist-info/licenses/LICENSE
rlinventoryopt-0.1.6.dist-info/METADATA
rlinventoryopt-0.1.6.dist-info/WHEEL
rlinventoryopt-0.1.6.dist-info/top_level.txt
rlinventoryopt-0.1.6.dist-info/RECORD
