Metadata-Version: 2.4
Name: RLInventoryOpt
Version: 0.1.6
Summary: Launching over version 0.1.2. Solving the actions list for inference.
Home-page: https://github.com/sebassaras02/rf_inventory_optimization
Author: Sebastian Sarasti
Author-email: Sebastian Sarasti <sebitas.alejo@hotmail.com>
License: MIT License
Project-URL: Homepage, https://github.com/sebassaras02/rf_inventory_optimization
Project-URL: Explanation, https://medium.com/@sebitas.alejo/reinforcement-learning-for-inventory-optimization-f63c26a59c19
Keywords: Reinforcement Learning,Q-Learning,Inventory Optimization
Classifier: License :: OSI Approved :: MIT License
Classifier: Programming Language :: Python
Classifier: Programming Language :: Python :: 3
Requires-Python: >=3.6
License-File: LICENSE
Requires-Dist: numpy==1.26.4
Requires-Dist: pandas==2.2.2
Requires-Dist: plotly==5.22.0
Dynamic: author
Dynamic: home-page
Dynamic: license-file
Dynamic: requires-python
